{
	"items": [
		{
			"title": "Carrot Cake",
			"body": null,
			"categories": "1"
		},
		{
			"title": "Cheese Cake",
			"body": null,
			"categories": "1"	
		},
		{
			"title": "KitKat Cake",
			"body": null,
			"categories": "1"	
		},
		{
			"title": "Apple Pie",
			"body": null,
			"categories": "1"
		},
		{
			"title": "Three Chocolate Cake",
			"body": null,
			"categories": "1"
		},
		{
			"title": "White Chocolate Sacher",
			"body": null,
			"categories": "1"	
		},
		{
			"title": "Pizza",
			"body": null,
			"categories": "2"	
		},
		{
			"title": "Spanish ommelette",
			"body": null,
			"categories": "2"	
		},
		{
			"title": "Hambuerguer",
			"body": null,
			"categories": "2"	
		}
	]
}
